[
  {
    "navdate": "2025-09-11",
    "nav": 18.1046
  },
  {
    "navdate": "2025-09-10",
    "nav": 17.9685
  },
  {
    "navdate": "2025-09-09",
    "nav": 17.9651
  },
  {
    "navdate": "2025-09-08",
    "nav": 17.9445
  },
  {
    "navdate": "2025-09-05",
    "nav": 17.8624
  },
  {
    "navdate": "2025-09-04",
    "nav": 17.8142
  },
  {
    "navdate": "2025-09-03",
    "nav": 17.6375
  },
  {
    "navdate": "2025-09-02",
    "nav": 17.4838
  },
  {
    "navdate": "2025-08-29",
    "nav": 17.5888
  },
  {
    "navdate": "2025-08-28",
    "nav": 17.7644
  },
  {
    "navdate": "2025-08-26",
    "nav": 17.6493
  },
  {
    "navdate": "2025-08-25",
    "nav": 17.5099
  },
  {
    "navdate": "2025-08-22",
    "nav": 17.5696
  },
  {
    "navdate": "2025-08-21",
    "nav": 17.2116
  },
  {
    "navdate": "2025-08-20",
    "nav": 17.3128
  },
  {
    "navdate": "2025-08-19",
    "nav": 17.4306
  },
  {
    "navdate": "2025-08-18",
    "nav": 17.7241
  },
  {
    "navdate": "2025-08-14",
    "nav": 17.8277
  },
  {
    "navdate": "2025-08-13",
    "nav": 17.8832
  },
  {
    "navdate": "2025-08-12",
    "nav": 17.8724
  },
  {
    "navdate": "2025-08-11",
    "nav": 17.6208
  },
  {
    "navdate": "2025-08-08",
    "nav": 17.6929
  },
  {
    "navdate": "2025-08-07",
    "nav": 17.5424
  },
  {
    "navdate": "2025-08-06",
    "nav": 17.4897
  },
  {
    "navdate": "2025-08-05",
    "nav": 17.2867
  },
  {
    "navdate": "2025-08-04",
    "nav": 17.3571
  },
  {
    "navdate": "2025-08-01",
    "nav": 17.0129
  },
  {
    "navdate": "2025-07-31",
    "nav": 17.3915
  },
  {
    "navdate": "2025-07-30",
    "nav": 17.431
  },
  {
    "navdate": "2025-07-29",
    "nav": 17.3244
  },
  {
    "navdate": "2025-07-28",
    "nav": 17.3079
  },
  {
    "navdate": "2025-07-25",
    "nav": 17.2422
  },
  {
    "navdate": "2025-07-24",
    "nav": 17.1666
  },
  {
    "navdate": "2025-07-23",
    "nav": 17.1325
  },
  {
    "navdate": "2025-07-22",
    "nav": 17.0386
  },
  {
    "navdate": "2025-07-21",
    "nav": 17.1183
  },
  {
    "navdate": "2025-07-18",
    "nav": 17.0308
  },
  {
    "navdate": "2025-07-17",
    "nav": 16.9846
  },
  {
    "navdate": "2025-07-16",
    "nav": 16.8385
  },
  {
    "navdate": "2025-07-15",
    "nav": 16.8259
  },
  {
    "navdate": "2025-07-14",
    "nav": 16.8375
  },
  {
    "navdate": "2025-07-11",
    "nav": 16.7569
  },
  {
    "navdate": "2025-07-10",
    "nav": 16.7392
  },
  {
    "navdate": "2025-07-09",
    "nav": 16.8087
  },
  {
    "navdate": "2025-07-08",
    "nav": 16.6743
  },
  {
    "navdate": "2025-07-07",
    "nav": 16.6812
  },
  {
    "navdate": "2025-07-03",
    "nav": 16.7569
  },
  {
    "navdate": "2025-07-02",
    "nav": 16.6266
  },
  {
    "navdate": "2025-07-01",
    "nav": 16.4916
  },
  {
    "navdate": "2025-06-30",
    "nav": 16.625
  },
  {
    "navdate": "2025-06-27",
    "nav": 16.5229
  },
  {
    "navdate": "2025-06-26",
    "nav": 16.4967
  },
  {
    "navdate": "2025-06-25",
    "nav": 16.3662
  },
  {
    "navdate": "2025-06-24",
    "nav": 16.3758
  },
  {
    "navdate": "2025-06-23",
    "nav": 16.2618
  },
  {
    "navdate": "2025-06-20",
    "nav": 16.0561
  },
  {
    "navdate": "2025-06-18",
    "nav": 16.0671
  },
  {
    "navdate": "2025-06-17",
    "nav": 16.0287
  },
  {
    "navdate": "2025-06-16",
    "nav": 16.1764
  },
  {
    "navdate": "2025-06-13",
    "nav": 15.9652
  },
  {
    "navdate": "2025-06-12",
    "nav": 16.0667
  },
  {
    "navdate": "2025-06-11",
    "nav": 16.0135
  },
  {
    "navdate": "2025-06-10",
    "nav": 16.0997
  },
  {
    "navdate": "2025-06-09",
    "nav": 15.9764
  },
  {
    "navdate": "2025-06-06",
    "nav": 16.0047
  },
  {
    "navdate": "2025-06-05",
    "nav": 15.8434
  },
  {
    "navdate": "2025-06-04",
    "nav": 16.0056
  },
  {
    "navdate": "2025-06-03",
    "nav": 15.8685
  },
  {
    "navdate": "2025-06-02",
    "nav": 15.7399
  },
  {
    "navdate": "2025-05-30",
    "nav": 15.6387
  },
  {
    "navdate": "2025-05-29",
    "nav": 15.6584
  },
  {
    "navdate": "2025-05-28",
    "nav": 15.6599
  },
  {
    "navdate": "2025-05-27",
    "nav": 15.6643
  },
  {
    "navdate": "2025-05-23",
    "nav": 15.3659
  },
  {
    "navdate": "2025-05-22",
    "nav": 15.5077
  },
  {
    "navdate": "2025-05-21",
    "nav": 15.464
  },
  {
    "navdate": "2025-05-20",
    "nav": 15.6571
  },
  {
    "navdate": "2025-05-19",
    "nav": 15.7218
  },
  {
    "navdate": "2025-05-16",
    "nav": 15.7196
  },
  {
    "navdate": "2025-05-15",
    "nav": 15.6546
  },
  {
    "navdate": "2025-05-14",
    "nav": 15.5879
  },
  {
    "navdate": "2025-05-13",
    "nav": 15.4252
  },
  {
    "navdate": "2025-05-12",
    "nav": 15.3212
  },
  {
    "navdate": "2025-05-09",
    "nav": 14.7287
  },
  {
    "navdate": "2025-05-08",
    "nav": 14.5963
  },
  {
    "navdate": "2025-05-07",
    "nav": 14.4047
  },
  {
    "navdate": "2025-05-06",
    "nav": 14.3448
  },
  {
    "navdate": "2025-05-05",
    "nav": 14.4205
  },
  {
    "navdate": "2025-05-02",
    "nav": 14.4534
  },
  {
    "navdate": "2025-04-30",
    "nav": 14.2725
  },
  {
    "navdate": "2025-04-29",
    "nav": 14.2777
  },
  {
    "navdate": "2025-04-28",
    "nav": 14.1918
  },
  {
    "navdate": "2025-04-25",
    "nav": 14.2601
  },
  {
    "navdate": "2025-04-24",
    "nav": 14.0888
  },
  {
    "navdate": "2025-04-23",
    "nav": 13.696
  },
  {
    "navdate": "2025-04-22",
    "nav": 13.3387
  },
  {
    "navdate": "2025-04-21",
    "nav": 13.0074
  },
  {
    "navdate": "2025-04-17",
    "nav": 13.4008
  },
  {
    "navdate": "2025-04-16",
    "nav": 13.4128
  },
  {
    "navdate": "2025-04-15",
    "nav": 13.8404
  },
  {
    "navdate": "2025-04-11",
    "nav": 13.8121
  },
  {
    "navdate": "2025-04-09",
    "nav": 14.2267
  },
  {
    "navdate": "2025-04-08",
    "nav": 12.5976
  },
  {
    "navdate": "2025-04-07",
    "nav": 12.8334
  },
  {
    "navdate": "2025-04-04",
    "nav": 12.7249
  },
  {
    "navdate": "2025-04-03",
    "nav": 13.6135
  },
  {
    "navdate": "2025-04-02",
    "nav": 14.3832
  },
  {
    "navdate": "2025-04-01",
    "nav": 14.2729
  },
  {
    "navdate": "2025-03-31",
    "nav": 14.1574
  },
  {
    "navdate": "2025-03-28",
    "nav": 14.1603
  },
  {
    "navdate": "2025-03-27",
    "nav": 14.5704
  },
  {
    "navdate": "2025-03-26",
    "nav": 14.6762
  },
  {
    "navdate": "2025-03-25",
    "nav": 14.9256
  },
  {
    "navdate": "2025-03-24",
    "nav": 14.8647
  },
  {
    "navdate": "2025-03-21",
    "nav": 14.6178
  },
  {
    "navdate": "2025-03-20",
    "nav": 14.576
  },
  {
    "navdate": "2025-03-19",
    "nav": 14.6524
  },
  {
    "navdate": "2025-03-18",
    "nav": 14.4932
  },
  {
    "navdate": "2025-03-17",
    "nav": 14.7586
  },
  {
    "navdate": "2025-03-13",
    "nav": 14.37
  },
  {
    "navdate": "2025-03-12",
    "nav": 14.6765
  },
  {
    "navdate": "2025-03-11",
    "nav": 14.524
  },
  {
    "navdate": "2025-03-10",
    "nav": 14.5502
  },
  {
    "navdate": "2025-03-07",
    "nav": 15.0956
  },
  {
    "navdate": "2025-03-06",
    "nav": 14.9872
  },
  {
    "navdate": "2025-03-05",
    "nav": 15.4171
  },
  {
    "navdate": "2025-03-04",
    "nav": 15.2619
  },
  {
    "navdate": "2025-03-03",
    "nav": 15.3083
  },
  {
    "navdate": "2025-02-28",
    "nav": 15.6653
  },
  {
    "navdate": "2025-02-27",
    "nav": 15.381
  },
  {
    "navdate": "2025-02-25",
    "nav": 15.7444
  },
  {
    "navdate": "2025-02-24",
    "nav": 15.8855
  },
  {
    "navdate": "2025-02-21",
    "nav": 16.0727
  },
  {
    "navdate": "2025-02-20",
    "nav": 16.4198
  },
  {
    "navdate": "2025-02-19",
    "nav": 16.5504
  },
  {
    "navdate": "2025-02-18",
    "nav": 16.5427
  },
  {
    "navdate": "2025-02-14",
    "nav": 16.4906
  },
  {
    "navdate": "2025-02-13",
    "nav": 16.4261
  },
  {
    "navdate": "2025-02-12",
    "nav": 16.1878
  },
  {
    "navdate": "2025-02-11",
    "nav": 16.1764
  },
  {
    "navdate": "2025-02-10",
    "nav": 16.3542
  },
  {
    "navdate": "2025-02-07",
    "nav": 16.135
  },
  {
    "navdate": "2025-02-06",
    "nav": 16.3625
  },
  {
    "navdate": "2025-02-05",
    "nav": 16.2133
  },
  {
    "navdate": "2025-02-04",
    "nav": 16.1265
  },
  {
    "navdate": "2025-02-03",
    "nav": 15.9251
  },
  {
    "navdate": "2025-01-31",
    "nav": 15.9735
  },
  {
    "navdate": "2025-01-30",
    "nav": 15.9846
  },
  {
    "navdate": "2025-01-29",
    "nav": 15.9119
  },
  {
    "navdate": "2025-01-28",
    "nav": 15.943
  },
  {
    "navdate": "2025-01-27",
    "nav": 15.6729
  },
  {
    "navdate": "2025-01-24",
    "nav": 16.1301
  },
  {
    "navdate": "2025-01-23",
    "nav": 16.2563
  },
  {
    "navdate": "2025-01-22",
    "nav": 16.2412
  },
  {
    "navdate": "2025-01-21",
    "nav": 16.0192
  },
  {
    "navdate": "2025-01-17",
    "nav": 15.9407
  },
  {
    "navdate": "2025-01-16",
    "nav": 15.6632
  },
  {
    "navdate": "2025-01-15",
    "nav": 15.7753
  },
  {
    "navdate": "2025-01-14",
    "nav": 15.4278
  },
  {
    "navdate": "2025-01-13",
    "nav": 15.4284
  },
  {
    "navdate": "2025-01-10",
    "nav": 15.3794
  },
  {
    "navdate": "2025-01-08",
    "nav": 15.6163
  },
  {
    "navdate": "2025-01-07",
    "nav": 15.5873
  },
  {
    "navdate": "2025-01-06",
    "nav": 15.892
  },
  {
    "navdate": "2025-01-03",
    "nav": 15.7087
  },
  {
    "navdate": "2025-01-02",
    "nav": 15.4544
  },
  {
    "navdate": "2024-12-31",
    "nav": 15.4528
  },
  {
    "navdate": "2024-12-30",
    "nav": 15.56
  },
  {
    "navdate": "2024-12-27",
    "nav": 15.787
  },
  {
    "navdate": "2024-12-26",
    "nav": 15.9437
  },
  {
    "navdate": "2024-12-24",
    "nav": 15.9519
  },
  {
    "navdate": "2024-12-23",
    "nav": 15.7141
  },
  {
    "navdate": "2024-12-20",
    "nav": 15.5608
  },
  {
    "navdate": "2024-12-19",
    "nav": 15.3907
  },
  {
    "navdate": "2024-12-18",
    "nav": 15.4382
  },
  {
    "navdate": "2024-12-17",
    "nav": 16.0128
  },
  {
    "navdate": "2024-12-16",
    "nav": 16.0637
  },
  {
    "navdate": "2024-12-13",
    "nav": 15.8375
  },
  {
    "navdate": "2024-12-12",
    "nav": 15.7229
  },
  {
    "navdate": "2024-12-11",
    "nav": 15.8257
  },
  {
    "navdate": "2024-12-10",
    "nav": 15.5402
  },
  {
    "navdate": "2024-12-09",
    "nav": 15.5708
  },
  {
    "navdate": "2024-12-06",
    "nav": 15.6894
  },
  {
    "navdate": "2024-12-05",
    "nav": 15.5594
  },
  {
    "navdate": "2024-12-04",
    "nav": 15.5993
  },
  {
    "navdate": "2024-12-03",
    "nav": 15.4192
  },
  {
    "navdate": "2024-12-02",
    "nav": 15.3605
  },
  {
    "navdate": "2024-11-29",
    "nav": 15.1588
  },
  {
    "navdate": "2024-11-27",
    "nav": 15.02
  },
  {
    "navdate": "2024-11-26",
    "nav": 15.1151
  },
  {
    "navdate": "2024-11-25",
    "nav": 15.0292
  },
  {
    "navdate": "2024-11-22",
    "nav": 15.0489
  },
  {
    "navdate": "2024-11-21",
    "nav": 15.0161
  },
  {
    "navdate": "2024-11-19",
    "nav": 14.9651
  },
  {
    "navdate": "2024-11-18",
    "nav": 14.8574
  },
  {
    "navdate": "2024-11-14",
    "nav": 15.1145
  },
  {
    "navdate": "2024-11-13",
    "nav": 15.218
  },
  {
    "navdate": "2024-11-12",
    "nav": 15.2423
  },
  {
    "navdate": "2024-11-11",
    "nav": 15.2656
  },
  {
    "navdate": "2024-11-08",
    "nav": 15.2728
  },
  {
    "navdate": "2024-11-07",
    "nav": 15.2569
  },
  {
    "navdate": "2024-11-06",
    "nav": 15.0044
  },
  {
    "navdate": "2024-11-05",
    "nav": 14.5857
  },
  {
    "navdate": "2024-11-04",
    "nav": 14.3931
  },
  {
    "navdate": "2024-10-31",
    "nav": 14.3385
  },
  {
    "navdate": "2024-10-30",
    "nav": 14.6958
  },
  {
    "navdate": "2024-10-29",
    "nav": 14.8124
  },
  {
    "navdate": "2024-10-28",
    "nav": 14.6688
  },
  {
    "navdate": "2024-10-25",
    "nav": 14.6706
  },
  {
    "navdate": "2024-10-24",
    "nav": 14.584
  },
  {
    "navdate": "2024-10-23",
    "nav": 14.465
  },
  {
    "navdate": "2024-10-22",
    "nav": 14.693
  },
  {
    "navdate": "2024-10-21",
    "nav": 14.6779
  },
  {
    "navdate": "2024-10-18",
    "nav": 14.6515
  },
  {
    "navdate": "2024-10-17",
    "nav": 14.5486
  },
  {
    "navdate": "2024-10-16",
    "nav": 14.5439
  },
  {
    "navdate": "2024-10-15",
    "nav": 14.5347
  },
  {
    "navdate": "2024-10-14",
    "nav": 14.7361
  },
  {
    "navdate": "2024-10-11",
    "nav": 14.6144
  },
  {
    "navdate": "2024-10-10",
    "nav": 14.5774
  },
  {
    "navdate": "2024-10-09",
    "nav": 14.5962
  },
  {
    "navdate": "2024-10-08",
    "nav": 14.4767
  },
  {
    "navdate": "2024-10-07",
    "nav": 14.2616
  },
  {
    "navdate": "2024-10-04",
    "nav": 14.4302
  },
  {
    "navdate": "2024-10-03",
    "nav": 14.2538
  },
  {
    "navdate": "2024-10-01",
    "nav": 14.2154
  },
  {
    "navdate": "2024-09-30",
    "nav": 14.4178
  },
  {
    "navdate": "2024-09-27",
    "nav": 14.3605
  },
  {
    "navdate": "2024-09-26",
    "nav": 14.4429
  },
  {
    "navdate": "2024-09-25",
    "nav": 14.3142
  },
  {
    "navdate": "2024-09-24",
    "nav": 14.3092
  },
  {
    "navdate": "2024-09-23",
    "nav": 14.2228
  },
  {
    "navdate": "2024-09-20",
    "nav": 14.177
  },
  {
    "navdate": "2024-09-19",
    "nav": 14.2332
  },
  {
    "navdate": "2024-09-18",
    "nav": 13.9122
  },
  {
    "navdate": "2024-09-17",
    "nav": 13.9756
  },
  {
    "navdate": "2024-09-16",
    "nav": 13.9797
  },
  {
    "navdate": "2024-09-13",
    "nav": 14.0502
  },
  {
    "navdate": "2024-09-12",
    "nav": 13.9946
  },
  {
    "navdate": "2024-09-11",
    "nav": 13.8554
  },
  {
    "navdate": "2024-09-10",
    "nav": 13.566
  },
  {
    "navdate": "2024-09-09",
    "nav": 13.4398
  },
  {
    "navdate": "2024-09-06",
    "nav": 13.2661
  },
  {
    "navdate": "2024-09-05",
    "nav": 13.6396
  },
  {
    "navdate": "2024-09-04",
    "nav": 13.6306
  },
  {
    "navdate": "2024-09-03",
    "nav": 13.6546
  },
  {
    "navdate": "2024-08-30",
    "nav": 14.0852
  },
  {
    "navdate": "2024-08-29",
    "nav": 13.9084
  },
  {
    "navdate": "2024-08-28",
    "nav": 13.9399
  },
  {
    "navdate": "2024-08-27",
    "nav": 14.1023
  },
  {
    "navdate": "2024-08-26",
    "nav": 14.0403
  },
  {
    "navdate": "2024-08-23",
    "nav": 14.1925
  },
  {
    "navdate": "2024-08-22",
    "nav": 14.0419
  },
  {
    "navdate": "2024-08-21",
    "nav": 14.275
  },
  {
    "navdate": "2024-08-20",
    "nav": 14.1766
  },
  {
    "navdate": "2024-08-19",
    "nav": 14.2341
  },
  {
    "navdate": "2024-08-16",
    "nav": 14.0556
  },
  {
    "navdate": "2024-08-14",
    "nav": 13.6995
  },
  {
    "navdate": "2024-08-13",
    "nav": 13.6935
  },
  {
    "navdate": "2024-08-12",
    "nav": 13.3604
  },
  {
    "navdate": "2024-08-09",
    "nav": 13.3284
  },
  {
    "navdate": "2024-08-08",
    "nav": 13.2611
  },
  {
    "navdate": "2024-08-07",
    "nav": 12.8671
  },
  {
    "navdate": "2024-08-06",
    "nav": 13.0141
  },
  {
    "navdate": "2024-08-05",
    "nav": 12.8732
  },
  {
    "navdate": "2024-08-02",
    "nav": 13.2476
  },
  {
    "navdate": "2024-08-01",
    "nav": 13.5661
  },
  {
    "navdate": "2024-07-31",
    "nav": 13.9085
  },
  {
    "navdate": "2024-07-30",
    "nav": 13.5009
  },
  {
    "navdate": "2024-07-29",
    "nav": 13.6911
  },
  {
    "navdate": "2024-07-26",
    "nav": 13.6653
  },
  {
    "navdate": "2024-07-25",
    "nav": 13.5237
  },
  {
    "navdate": "2024-07-24",
    "nav": 13.6681
  },
  {
    "navdate": "2024-07-23",
    "nav": 14.1793
  },
  {
    "navdate": "2024-07-22",
    "nav": 14.2294
  },
  {
    "navdate": "2024-07-19",
    "nav": 14.0108
  },
  {
    "navdate": "2024-07-18",
    "nav": 14.1419
  },
  {
    "navdate": "2024-07-16",
    "nav": 14.6287
  },
  {
    "navdate": "2024-07-15",
    "nav": 14.6186
  },
  {
    "navdate": "2024-07-12",
    "nav": 14.5754
  },
  {
    "navdate": "2024-07-11",
    "nav": 14.4891
  },
  {
    "navdate": "2024-07-10",
    "nav": 14.8145
  },
  {
    "navdate": "2024-07-09",
    "nav": 14.6541
  },
  {
    "navdate": "2024-07-08",
    "nav": 14.6435
  },
  {
    "navdate": "2024-07-05",
    "nav": 14.6147
  },
  {
    "navdate": "2024-07-03",
    "nav": 14.4732
  },
  {
    "navdate": "2024-07-02",
    "nav": 14.3444
  },
  {
    "navdate": "2024-07-01",
    "nav": 14.183
  },
  {
    "navdate": "2024-06-28",
    "nav": 14.0998
  },
  {
    "navdate": "2024-06-27",
    "nav": 14.1819
  },
  {
    "navdate": "2024-06-26",
    "nav": 14.1638
  },
  {
    "navdate": "2024-06-25",
    "nav": 14.1091
  },
  {
    "navdate": "2024-06-24",
    "nav": 13.9619
  },
  {
    "navdate": "2024-06-21",
    "nav": 14.1354
  },
  {
    "navdate": "2024-06-20",
    "nav": 14.1622
  },
  {
    "navdate": "2024-06-18",
    "nav": 14.2674
  },
  {
    "navdate": "2024-06-14",
    "nav": 14.1013
  },
  {
    "navdate": "2024-06-13",
    "nav": 14.0407
  },
  {
    "navdate": "2024-06-12",
    "nav": 13.9638
  },
  {
    "navdate": "2024-06-11",
    "nav": 13.7722
  },
  {
    "navdate": "2024-06-10",
    "nav": 13.6732
  },
  {
    "navdate": "2024-06-07",
    "nav": 13.6101
  },
  {
    "navdate": "2024-06-06",
    "nav": 13.6298
  },
  {
    "navdate": "2024-06-05",
    "nav": 13.6275
  },
  {
    "navdate": "2024-06-04",
    "nav": 13.374
  },
  {
    "navdate": "2024-06-03",
    "nav": 13.2655
  },
  {
    "navdate": "2024-05-31",
    "nav": 13.2578
  },
  {
    "navdate": "2024-05-30",
    "nav": 13.2787
  },
  {
    "navdate": "2024-05-29",
    "nav": 13.4047
  },
  {
    "navdate": "2024-05-28",
    "nav": 13.4734
  },
  {
    "navdate": "2024-05-24",
    "nav": 13.4243
  },
  {
    "navdate": "2024-05-23",
    "nav": 13.3099
  },
  {
    "navdate": "2024-05-22",
    "nav": 13.3685
  },
  {
    "navdate": "2024-05-21",
    "nav": 13.3959
  },
  {
    "navdate": "2024-05-17",
    "nav": 13.2961
  },
  {
    "navdate": "2024-05-16",
    "nav": 13.3079
  },
  {
    "navdate": "2024-05-15",
    "nav": 13.3356
  },
  {
    "navdate": "2024-05-14",
    "nav": 13.14
  },
  {
    "navdate": "2024-05-13",
    "nav": 13.0514
  },
  {
    "navdate": "2024-05-10",
    "nav": 13.021
  },
  {
    "navdate": "2024-05-09",
    "nav": 12.9864
  },
  {
    "navdate": "2024-05-08",
    "nav": 12.9682
  },
  {
    "navdate": "2024-05-07",
    "nav": 12.971
  },
  {
    "navdate": "2024-05-06",
    "nav": 12.9677
  },
  {
    "navdate": "2024-05-03",
    "nav": 12.8089
  },
  {
    "navdate": "2024-05-02",
    "nav": 12.571
  },
  {
    "navdate": "2024-04-30",
    "nav": 12.5092
  },
  {
    "navdate": "2024-04-29",
    "nav": 12.7427
  },
  {
    "navdate": "2024-04-26",
    "nav": 12.6827
  },
  {
    "navdate": "2024-04-25",
    "nav": 12.4826
  },
  {
    "navdate": "2024-04-24",
    "nav": 12.5396
  },
  {
    "navdate": "2024-04-23",
    "nav": 12.512
  },
  {
    "navdate": "2024-04-22",
    "nav": 12.3313
  },
  {
    "navdate": "2024-04-19",
    "nav": 12.2244
  },
  {
    "navdate": "2024-04-18",
    "nav": 12.4797
  },
  {
    "navdate": "2024-04-16",
    "nav": 12.7062
  },
  {
    "navdate": "2024-04-15",
    "nav": 12.6932
  },
  {
    "navdate": "2024-04-12",
    "nav": 12.8994
  },
  {
    "navdate": "2024-04-10",
    "nav": 12.88
  },
  {
    "navdate": "2024-04-09",
    "nav": 13.0078
  },
  {
    "navdate": "2024-04-08",
    "nav": 12.9582
  },
  {
    "navdate": "2024-04-05",
    "nav": 12.9788
  },
  {
    "navdate": "2024-04-04",
    "nav": 12.8208
  },
  {
    "navdate": "2024-04-03",
    "nav": 13.0197
  },
  {
    "navdate": "2024-04-02",
    "nav": 12.9817
  },
  {
    "navdate": "2024-04-01",
    "nav": 13.1062
  },
  {
    "navdate": "2024-03-31",
    "nav": 13.0792
  },
  {
    "navdate": "2024-03-28",
    "nav": 13.0801
  },
  {
    "navdate": "2024-03-27",
    "nav": 13.0915
  },
  {
    "navdate": "2024-03-26",
    "nav": 13.0454
  },
  {
    "navdate": "2024-03-22",
    "nav": 13.1325
  },
  {
    "navdate": "2024-03-21",
    "nav": 13.0842
  },
  {
    "navdate": "2024-03-20",
    "nav": 13.023
  },
  {
    "navdate": "2024-03-19",
    "nav": 12.8476
  },
  {
    "navdate": "2024-03-18",
    "nav": 12.809
  },
  {
    "navdate": "2024-03-15",
    "nav": 12.6822
  },
  {
    "navdate": "2024-03-14",
    "nav": 12.8273
  },
  {
    "navdate": "2024-03-13",
    "nav": 12.8702
  },
  {
    "navdate": "2024-03-12",
    "nav": 12.9531
  },
  {
    "navdate": "2024-03-11",
    "nav": 12.7528
  },
  {
    "navdate": "2024-03-07",
    "nav": 13.0159
  },
  {
    "navdate": "2024-03-06",
    "nav": 12.8352
  },
  {
    "navdate": "2024-03-05",
    "nav": 12.7536
  },
  {
    "navdate": "2024-03-04",
    "nav": 12.9833
  },
  {
    "navdate": "2024-03-01",
    "nav": 13.0338
  },
  {
    "navdate": "2024-02-29",
    "nav": 12.8581
  },
  {
    "navdate": "2024-02-28",
    "nav": 12.7346
  },
  {
    "navdate": "2024-02-27",
    "nav": 12.7986
  },
  {
    "navdate": "2024-02-26",
    "nav": 12.771
  },
  {
    "navdate": "2024-02-23",
    "nav": 12.7751
  },
  {
    "navdate": "2024-02-22",
    "nav": 12.8294
  },
  {
    "navdate": "2024-02-21",
    "nav": 12.4488
  },
  {
    "navdate": "2024-02-20",
    "nav": 12.5095
  },
  {
    "navdate": "2024-02-16",
    "nav": 12.6198
  },
  {
    "navdate": "2024-02-15",
    "nav": 12.7305
  },
  {
    "navdate": "2024-02-14",
    "nav": 12.7133
  },
  {
    "navdate": "2024-02-13",
    "nav": 12.5548
  },
  {
    "navdate": "2024-02-12",
    "nav": 12.7518
  },
  {
    "navdate": "2024-02-09",
    "nav": 12.8104
  },
  {
    "navdate": "2024-02-08",
    "nav": 12.6778
  },
  {
    "navdate": "2024-02-07",
    "nav": 12.6574
  },
  {
    "navdate": "2024-02-06",
    "nav": 12.5413
  },
  {
    "navdate": "2024-02-05",
    "nav": 12.5649
  },
  {
    "navdate": "2024-02-02",
    "nav": 12.5588
  },
  {
    "navdate": "2024-02-01",
    "nav": 12.3636
  },
  {
    "navdate": "2024-01-31",
    "nav": 12.2341
  },
  {
    "navdate": "2024-01-30",
    "nav": 12.4826
  },
  {
    "navdate": "2024-01-29",
    "nav": 12.5716
  },
  {
    "navdate": "2024-01-25",
    "nav": 12.5122
  },
  {
    "navdate": "2024-01-24",
    "nav": 12.504
  },
  {
    "navdate": "2024-01-23",
    "nav": 12.4303
  },
  {
    "navdate": "2024-01-19",
    "nav": 12.3713
  },
  {
    "navdate": "2024-01-18",
    "nav": 12.1336
  },
  {
    "navdate": "2024-01-17",
    "nav": 11.9593
  },
  {
    "navdate": "2024-01-16",
    "nav": 12.0049
  },
  {
    "navdate": "2024-01-12",
    "nav": 12.0087
  },
  {
    "navdate": "2024-01-11",
    "nav": 11.9935
  },
  {
    "navdate": "2024-01-10",
    "nav": 12.0049
  },
  {
    "navdate": "2024-01-09",
    "nav": 11.9197
  },
  {
    "navdate": "2024-01-08",
    "nav": 11.8914
  },
  {
    "navdate": "2024-01-05",
    "nav": 11.6614
  },
  {
    "navdate": "2024-01-04",
    "nav": 11.662
  },
  {
    "navdate": "2024-01-03",
    "nav": 11.7279
  },
  {
    "navdate": "2024-01-02",
    "nav": 11.8524
  },
  {
    "navdate": "2023-12-29",
    "nav": 12.0247
  },
  {
    "navdate": "2023-12-28",
    "nav": 12.0918
  },
  {
    "navdate": "2023-12-27",
    "nav": 12.1118
  },
  {
    "navdate": "2023-12-26",
    "nav": 12.0715
  },
  {
    "navdate": "2023-12-22",
    "nav": 12.0125
  },
  {
    "navdate": "2023-12-21",
    "nav": 12.0015
  },
  {
    "navdate": "2023-12-19",
    "nav": 12.0283
  },
  {
    "navdate": "2023-12-18",
    "nav": 11.9451
  },
  {
    "navdate": "2023-12-15",
    "nav": 11.8939
  },
  {
    "navdate": "2023-12-14",
    "nav": 11.8574
  },
  {
    "navdate": "2023-12-13",
    "nav": 11.8821
  },
  {
    "navdate": "2023-12-12",
    "nav": 11.7313
  },
  {
    "navdate": "2023-12-11",
    "nav": 11.6372
  },
  {
    "navdate": "2023-12-08",
    "nav": 11.537
  },
  {
    "navdate": "2023-12-07",
    "nav": 11.4928
  },
  {
    "navdate": "2023-12-06",
    "nav": 11.3229
  },
  {
    "navdate": "2023-12-05",
    "nav": 11.3931
  },
  {
    "navdate": "2023-12-04",
    "nav": 11.3576
  },
  {
    "navdate": "2023-12-01",
    "nav": 11.4751
  },
  {
    "navdate": "2023-11-30",
    "nav": 11.4376
  },
  {
    "navdate": "2023-11-29",
    "nav": 11.4606
  },
  {
    "navdate": "2023-11-28",
    "nav": 11.4873
  },
  {
    "navdate": "2023-11-24",
    "nav": 11.4643
  },
  {
    "navdate": "2023-11-22",
    "nav": 11.4749
  },
  {
    "navdate": "2023-11-21",
    "nav": 11.4275
  },
  {
    "navdate": "2023-11-20",
    "nav": 11.4927
  },
  {
    "navdate": "2023-11-17",
    "nav": 11.3485
  },
  {
    "navdate": "2023-11-16",
    "nav": 11.3416
  },
  {
    "navdate": "2023-11-15",
    "nav": 11.3146
  },
  {
    "navdate": "2023-11-13",
    "nav": 11.1007
  },
  {
    "navdate": "2023-11-10",
    "nav": 11.138
  },
  {
    "navdate": "2023-11-09",
    "nav": 10.8826
  },
  {
    "navdate": "2023-11-08",
    "nav": 10.9706
  },
  {
    "navdate": "2023-11-07",
    "nav": 10.9576
  },
  {
    "navdate": "2023-11-06",
    "nav": 10.8515
  },
  {
    "navdate": "2023-11-03",
    "nav": 10.8177
  },
  {
    "navdate": "2023-11-02",
    "nav": 10.6892
  },
  {
    "navdate": "2023-11-01",
    "nav": 10.5096
  },
  {
    "navdate": "2023-10-31",
    "nav": 10.3254
  },
  {
    "navdate": "2023-10-30",
    "nav": 10.2724
  },
  {
    "navdate": "2023-10-27",
    "nav": 10.159
  },
  {
    "navdate": "2023-10-26",
    "nav": 10.1076
  },
  {
    "navdate": "2023-10-25",
    "nav": 10.2916
  },
  {
    "navdate": "2023-10-23",
    "nav": 10.4534
  },
  {
    "navdate": "2023-10-20",
    "nav": 10.427
  },
  {
    "navdate": "2023-10-19",
    "nav": 10.596
  },
  {
    "navdate": "2023-10-18",
    "nav": 10.684
  },
  {
    "navdate": "2023-10-17",
    "nav": 10.8367
  },
  {
    "navdate": "2023-10-16",
    "nav": 10.8741
  },
  {
    "navdate": "2023-10-13",
    "nav": 10.7469
  },
  {
    "navdate": "2023-10-12",
    "nav": 10.8726
  },
  {
    "navdate": "2023-10-11",
    "nav": 10.9209
  },
  {
    "navdate": "2023-10-10",
    "nav": 10.8455
  },
  {
    "navdate": "2023-10-06",
    "nav": 10.7305
  },
  {
    "navdate": "2023-10-05",
    "nav": 10.5524
  },
  {
    "navdate": "2023-10-04",
    "nav": 10.5921
  },
  {
    "navdate": "2023-10-03",
    "nav": 10.4324
  },
  {
    "navdate": "2023-09-29",
    "nav": 10.5231
  },
  {
    "navdate": "2023-09-27",
    "nav": 10.4466
  },
  {
    "navdate": "2023-09-26",
    "nav": 10.4249
  },
  {
    "navdate": "2023-09-25",
    "nav": 10.5673
  },
  {
    "navdate": "2023-09-22",
    "nav": 10.5005
  },
  {
    "navdate": "2023-09-21",
    "nav": 10.5221
  },
  {
    "navdate": "2023-09-20",
    "nav": 10.733
  },
  {
    "navdate": "2023-09-18",
    "nav": 10.909
  },
  {
    "navdate": "2023-09-15",
    "nav": 10.8735
  },
  {
    "navdate": "2023-09-14",
    "nav": 11.057
  },
  {
    "navdate": "2023-09-13",
    "nav": 10.9643
  },
  {
    "navdate": "2023-09-12",
    "nav": 10.9253
  },
  {
    "navdate": "2023-09-11",
    "nav": 11.0353
  },
  {
    "navdate": "2023-09-08",
    "nav": 10.9438
  },
  {
    "navdate": "2023-09-07",
    "nav": 10.9313
  },
  {
    "navdate": "2023-09-06",
    "nav": 11.0001
  },
  {
    "navdate": "2023-09-05",
    "nav": 11.0788
  },
  {
    "navdate": "2023-09-01",
    "nav": 11.03
  },
  {
    "navdate": "2023-08-31",
    "nav": 11.039
  },
  {
    "navdate": "2023-08-30",
    "nav": 11.0222
  },
  {
    "navdate": "2023-08-29",
    "nav": 10.9452
  },
  {
    "navdate": "2023-08-28",
    "nav": 10.7097
  },
  {
    "navdate": "2023-08-25",
    "nav": 10.6372
  },
  {
    "navdate": "2023-08-24",
    "nav": 10.5353
  },
  {
    "navdate": "2023-08-23",
    "nav": 10.8189
  },
  {
    "navdate": "2023-08-22",
    "nav": 10.6679
  },
  {
    "navdate": "2023-08-21",
    "nav": 10.6933
  },
  {
    "navdate": "2023-08-18",
    "nav": 10.5184
  },
  {
    "navdate": "2023-08-17",
    "nav": 10.5377
  },
  {
    "navdate": "2023-08-16",
    "nav": 10.6302
  },
  {
    "navdate": "2023-08-14",
    "nav": 10.8637
  },
  {
    "navdate": "2023-08-11",
    "nav": 10.7155
  },
  {
    "navdate": "2023-08-10",
    "nav": 10.7935
  },
  {
    "navdate": "2023-08-09",
    "nav": 10.7707
  },
  {
    "navdate": "2023-08-08",
    "nav": 10.8898
  },
  {
    "navdate": "2023-08-07",
    "nav": 10.9788
  },
  {
    "navdate": "2023-08-04",
    "nav": 10.8921
  },
  {
    "navdate": "2023-08-03",
    "nav": 10.9382
  },
  {
    "navdate": "2023-08-02",
    "nav": 10.9263
  },
  {
    "navdate": "2023-08-01",
    "nav": 11.1392
  },
  {
    "navdate": "2023-07-31",
    "nav": 11.1625
  },
  {
    "navdate": "2023-07-28",
    "nav": 11.1581
  },
  {
    "navdate": "2023-07-27",
    "nav": 10.9222
  },
  {
    "navdate": "2023-07-26",
    "nav": 10.946
  },
  {
    "navdate": "2023-07-25",
    "nav": 10.9658
  },
  {
    "navdate": "2023-07-24",
    "nav": 10.9023
  },
  {
    "navdate": "2023-07-21",
    "nav": 10.8999
  },
  {
    "navdate": "2023-07-20",
    "nav": 10.9178
  },
  {
    "navdate": "2023-07-19",
    "nav": 11.1792
  },
  {
    "navdate": "2023-07-18",
    "nav": 11.1828
  },
  {
    "navdate": "2023-07-17",
    "nav": 11.1063
  },
  {
    "navdate": "2023-07-14",
    "nav": 10.9965
  },
  {
    "navdate": "2023-07-13",
    "nav": 11.0043
  },
  {
    "navdate": "2023-07-12",
    "nav": 10.839
  },
  {
    "navdate": "2023-07-11",
    "nav": 10.7152
  },
  {
    "navdate": "2023-07-10",
    "nav": 10.6997
  },
  {
    "navdate": "2023-07-07",
    "nav": 10.7005
  },
  {
    "navdate": "2023-07-06",
    "nav": 10.7087
  },
  {
    "navdate": "2023-07-05",
    "nav": 10.7515
  },
  {
    "navdate": "2023-07-03",
    "nav": 10.715
  },
  {
    "navdate": "2023-06-30",
    "nav": 10.7183
  },
  {
    "navdate": "2023-06-28",
    "nav": 10.5635
  },
  {
    "navdate": "2023-06-27",
    "nav": 10.5437
  },
  {
    "navdate": "2023-06-26",
    "nav": 10.3647
  },
  {
    "navdate": "2023-06-23",
    "nav": 10.5178
  },
  {
    "navdate": "2023-06-22",
    "nav": 10.6079
  },
  {
    "navdate": "2023-06-21",
    "nav": 10.5075
  },
  {
    "navdate": "2023-06-20",
    "nav": 10.6525
  },
  {
    "navdate": "2023-06-16",
    "nav": 10.6336
  },
  {
    "navdate": "2023-06-15",
    "nav": 10.7456
  },
  {
    "navdate": "2023-06-14",
    "nav": 10.6336
  },
  {
    "navdate": "2023-06-13",
    "nav": 10.5694
  },
  {
    "navdate": "2023-06-12",
    "nav": 10.4946
  },
  {
    "navdate": "2023-06-09",
    "nav": 10.3104
  },
  {
    "navdate": "2023-06-08",
    "nav": 10.2983
  },
  {
    "navdate": "2023-06-07",
    "nav": 10.1645
  },
  {
    "navdate": "2023-06-06",
    "nav": 10.3586
  },
  {
    "navdate": "2023-06-05",
    "nav": 10.3495
  },
  {
    "navdate": "2023-06-02",
    "nav": 10.3107
  },
  {
    "navdate": "2023-06-01",
    "nav": 10.2533
  },
  {
    "navdate": "2023-05-31",
    "nav": 10.1473
  },
  {
    "navdate": "2023-05-30",
    "nav": 10.2256
  },
  {
    "navdate": "2023-05-26",
    "nav": 10.1843
  },
  {
    "navdate": "2023-05-25",
    "nav": 9.9318
  },
  {
    "navdate": "2023-05-24",
    "nav": 9.6909
  },
  {
    "navdate": "2023-05-23",
    "nav": 9.7483
  },
  {
    "navdate": "2023-05-22",
    "nav": 9.8748
  },
  {
    "navdate": "2023-05-19",
    "nav": 9.8312
  },
  {
    "navdate": "2023-05-18",
    "nav": 9.8276
  },
  {
    "navdate": "2023-05-17",
    "nav": 9.6409
  },
  {
    "navdate": "2023-05-16",
    "nav": 9.5112
  },
  {
    "navdate": "2023-05-15",
    "nav": 9.5041
  },
  {
    "navdate": "2023-05-12",
    "nav": 9.439
  },
  {
    "navdate": "2023-05-11",
    "nav": 9.4589
  },
  {
    "navdate": "2023-05-10",
    "nav": 9.4265
  },
  {
    "navdate": "2023-05-09",
    "nav": 9.323
  },
  {
    "navdate": "2023-05-08",
    "nav": 9.357
  },
  {
    "navdate": "2023-05-05",
    "nav": 9.3318
  },
  {
    "navdate": "2023-05-04",
    "nav": 9.137
  },
  {
    "navdate": "2023-05-03",
    "nav": 9.1837
  },
  {
    "navdate": "2023-05-02",
    "nav": 9.2322
  },
  {
    "navdate": "2023-04-28",
    "nav": 9.3291
  },
  {
    "navdate": "2023-04-27",
    "nav": 9.2537
  },
  {
    "navdate": "2023-04-26",
    "nav": 9.0343
  },
  {
    "navdate": "2023-04-25",
    "nav": 8.9757
  },
  {
    "navdate": "2023-04-24",
    "nav": 9.1648
  },
  {
    "navdate": "2023-04-21",
    "nav": 9.1995
  },
  {
    "navdate": "2023-04-20",
    "nav": 9.1901
  },
  {
    "navdate": "2023-04-19",
    "nav": 9.2584
  },
  {
    "navdate": "2023-04-18",
    "nav": 9.2555
  },
  {
    "navdate": "2023-04-17",
    "nav": 9.2385
  },
  {
    "navdate": "2023-04-13",
    "nav": 9.2578
  },
  {
    "navdate": "2023-04-12",
    "nav": 9.0843
  },
  {
    "navdate": "2023-04-11",
    "nav": 9.1687
  },
  {
    "navdate": "2023-04-10",
    "nav": 9.2109
  },
  {
    "navdate": "2023-04-06",
    "nav": 9.2262
  },
  {
    "navdate": "2023-04-05",
    "nav": 9.1829
  },
  {
    "navdate": "2023-04-03",
    "nav": 9.3315
  },
  {
    "navdate": "2023-03-31",
    "nav": 9.3361
  },
  {
    "navdate": "2023-03-29",
    "nav": 9.1152
  },
  {
    "navdate": "2023-03-28",
    "nav": 8.9353
  },
  {
    "navdate": "2023-03-27",
    "nav": 8.9957
  },
  {
    "navdate": "2023-03-24",
    "nav": 9.0496
  },
  {
    "navdate": "2023-03-23",
    "nav": 9.0142
  },
  {
    "navdate": "2023-03-22",
    "nav": 8.9562
  },
  {
    "navdate": "2023-03-21",
    "nav": 9.0805
  },
  {
    "navdate": "2023-03-20",
    "nav": 8.9334
  },
  {
    "navdate": "2023-03-17",
    "nav": 8.9001
  },
  {
    "navdate": "2023-03-16",
    "nav": 8.968
  },
  {
    "navdate": "2023-03-15",
    "nav": 8.7138
  },
  {
    "navdate": "2023-03-14",
    "nav": 8.6631
  },
  {
    "navdate": "2023-03-13",
    "nav": 8.4245
  },
  {
    "navdate": "2023-03-10",
    "nav": 8.3696
  },
  {
    "navdate": "2023-03-09",
    "nav": 8.4764
  },
  {
    "navdate": "2023-03-08",
    "nav": 8.6488
  },
  {
    "navdate": "2023-03-06",
    "nav": 8.6755
  },
  {
    "navdate": "2023-03-03",
    "nav": 8.7222
  },
  {
    "navdate": "2023-03-02",
    "nav": 8.5822
  },
  {
    "navdate": "2023-03-01",
    "nav": 8.5045
  },
  {
    "navdate": "2023-02-28",
    "nav": 8.5911
  },
  {
    "navdate": "2023-02-27",
    "nav": 8.6264
  },
  {
    "navdate": "2023-02-24",
    "nav": 8.5466
  },
  {
    "navdate": "2023-02-23",
    "nav": 8.6976
  },
  {
    "navdate": "2023-02-22",
    "nav": 8.6247
  },
  {
    "navdate": "2023-02-21",
    "nav": 8.6114
  },
  {
    "navdate": "2023-02-17",
    "nav": 8.8301
  },
  {
    "navdate": "2023-02-16",
    "nav": 8.8726
  },
  {
    "navdate": "2023-02-15",
    "nav": 9.0703
  },
  {
    "navdate": "2023-02-14",
    "nav": 8.9828
  },
  {
    "navdate": "2023-02-13",
    "nav": 8.9192
  },
  {
    "navdate": "2023-02-10",
    "nav": 8.7663
  },
  {
    "navdate": "2023-02-09",
    "nav": 8.8227
  },
  {
    "navdate": "2023-02-08",
    "nav": 8.9097
  },
  {
    "navdate": "2023-02-07",
    "nav": 9.0771
  },
  {
    "navdate": "2023-02-06",
    "nav": 8.8684
  },
  {
    "navdate": "2023-02-03",
    "nav": 8.9214
  },
  {
    "navdate": "2023-02-02",
    "nav": 9.0524
  },
  {
    "navdate": "2023-02-01",
    "nav": 8.733
  },
  {
    "navdate": "2023-01-31",
    "nav": 8.5389
  },
  {
    "navdate": "2023-01-30",
    "nav": 8.3972
  },
  {
    "navdate": "2023-01-27",
    "nav": 8.564
  },
  {
    "navdate": "2023-01-25",
    "nav": 8.3257
  },
  {
    "navdate": "2023-01-24",
    "nav": 8.3456
  },
  {
    "navdate": "2023-01-23",
    "nav": 8.3311
  },
  {
    "navdate": "2023-01-20",
    "nav": 8.1492
  },
  {
    "navdate": "2023-01-19",
    "nav": 7.9375
  },
  {
    "navdate": "2023-01-18",
    "nav": 8.0456
  },
  {
    "navdate": "2023-01-17",
    "nav": 8.1614
  },
  {
    "navdate": "2023-01-13",
    "nav": 8.1176
  },
  {
    "navdate": "2023-01-12",
    "nav": 8.0889
  },
  {
    "navdate": "2023-01-11",
    "nav": 8.0479
  },
  {
    "navdate": "2023-01-10",
    "nav": 7.9576
  },
  {
    "navdate": "2023-01-09",
    "nav": 7.9036
  },
  {
    "navdate": "2023-01-06",
    "nav": 7.8813
  },
  {
    "navdate": "2023-01-05",
    "nav": 7.6751
  },
  {
    "navdate": "2023-01-04",
    "nav": 7.8159
  },
  {
    "navdate": "2023-01-03",
    "nav": 7.7677
  },
  {
    "navdate": "2022-12-30",
    "nav": 7.823
  },
  {
    "navdate": "2022-12-29",
    "nav": 7.8342
  },
  {
    "navdate": "2022-12-28",
    "nav": 7.6492
  },
  {
    "navdate": "2022-12-27",
    "nav": 7.7407
  },
  {
    "navdate": "2022-12-23",
    "nav": 7.8627
  },
  {
    "navdate": "2022-12-22",
    "nav": 7.8233
  },
  {
    "navdate": "2022-12-21",
    "nav": 8.0318
  },
  {
    "navdate": "2022-12-20",
    "nav": 7.9122
  },
  {
    "navdate": "2022-12-19",
    "nav": 7.9067
  },
  {
    "navdate": "2022-12-16",
    "nav": 8.0327
  },
  {
    "navdate": "2022-12-15",
    "nav": 8.0809
  },
  {
    "navdate": "2022-12-14",
    "nav": 8.364
  },
  {
    "navdate": "2022-12-13",
    "nav": 8.4494
  },
  {
    "navdate": "2022-12-12",
    "nav": 8.352
  },
  {
    "navdate": "2022-12-09",
    "nav": 8.2079
  },
  {
    "navdate": "2022-12-08",
    "nav": 8.2674
  },
  {
    "navdate": "2022-12-07",
    "nav": 8.1929
  },
  {
    "navdate": "2022-12-06",
    "nav": 8.2041
  },
  {
    "navdate": "2022-12-05",
    "nav": 8.3009
  },
  {
    "navdate": "2022-12-02",
    "nav": 8.4042
  },
  {
    "navdate": "2022-12-01",
    "nav": 8.4347
  },
  {
    "navdate": "2022-11-30",
    "nav": 8.4738
  },
  {
    "navdate": "2022-11-29",
    "nav": 8.1284
  },
  {
    "navdate": "2022-11-28",
    "nav": 8.1923
  },
  {
    "navdate": "2022-11-25",
    "nav": 8.292
  },
  {
    "navdate": "2022-11-23",
    "nav": 8.3793
  },
  {
    "navdate": "2022-11-22",
    "nav": 8.2946
  },
  {
    "navdate": "2022-11-21",
    "nav": 8.1764
  },
  {
    "navdate": "2022-11-18",
    "nav": 8.2558
  },
  {
    "navdate": "2022-11-17",
    "nav": 8.2493
  },
  {
    "navdate": "2022-11-16",
    "nav": 8.2357
  },
  {
    "navdate": "2022-11-15",
    "nav": 8.3616
  },
  {
    "navdate": "2022-11-14",
    "nav": 8.2258
  },
  {
    "navdate": "2022-11-11",
    "nav": 8.2491
  },
  {
    "navdate": "2022-11-10",
    "nav": 8.2074
  },
  {
    "navdate": "2022-11-09",
    "nav": 7.6127
  },
  {
    "navdate": "2022-11-07",
    "nav": 7.807
  },
  {
    "navdate": "2022-11-04",
    "nav": 7.7535
  },
  {
    "navdate": "2022-11-03",
    "nav": 7.6669
  },
  {
    "navdate": "2022-11-02",
    "nav": 7.8103
  },
  {
    "navdate": "2022-11-01",
    "nav": 8.0787
  },
  {
    "navdate": "2022-10-31",
    "nav": 8.1307
  },
  {
    "navdate": "2022-10-28",
    "nav": 8.2325
  },
  {
    "navdate": "2022-10-27",
    "nav": 7.9786
  },
  {
    "navdate": "2022-10-25",
    "nav": 8.353
  },
  {
    "navdate": "2022-10-21",
    "nav": 8.1082
  },
  {
    "navdate": "2022-10-20",
    "nav": 7.9516
  },
  {
    "navdate": "2022-10-19",
    "nav": 7.9147
  },
  {
    "navdate": "2022-10-18",
    "nav": 7.9327
  },
  {
    "navdate": "2022-10-17",
    "nav": 7.89
  },
  {
    "navdate": "2022-10-14",
    "nav": 7.6275
  },
  {
    "navdate": "2022-10-13",
    "nav": 7.8704
  },
  {
    "navdate": "2022-10-12",
    "nav": 7.6763
  },
  {
    "navdate": "2022-10-11",
    "nav": 7.694
  },
  {
    "navdate": "2022-10-10",
    "nav": 7.7905
  },
  {
    "navdate": "2022-10-07",
    "nav": 7.8711
  },
  {
    "navdate": "2022-10-06",
    "nav": 8.1217
  },
  {
    "navdate": "2022-10-04",
    "nav": 8.1641
  },
  {
    "navdate": "2022-10-03",
    "nav": 7.9491
  },
  {
    "navdate": "2022-09-30",
    "nav": 7.7524
  },
  {
    "navdate": "2022-09-29",
    "nav": 7.9178
  },
  {
    "navdate": "2022-09-28",
    "nav": 8.1529
  },
  {
    "navdate": "2022-09-27",
    "nav": 7.9452
  },
  {
    "navdate": "2022-09-26",
    "nav": 7.952
  },
  {
    "navdate": "2022-09-23",
    "nav": 7.9301
  },
  {
    "navdate": "2022-09-22",
    "nav": 8.0426
  },
  {
    "navdate": "2022-09-21",
    "nav": 8.0579
  },
  {
    "navdate": "2022-09-20",
    "nav": 8.1791
  },
  {
    "navdate": "2022-09-19",
    "nav": 8.2481
  },
  {
    "navdate": "2022-09-16",
    "nav": 8.2005
  },
  {
    "navdate": "2022-09-15",
    "nav": 8.2217
  },
  {
    "navdate": "2022-09-14",
    "nav": 8.3632
  },
  {
    "navdate": "2022-09-13",
    "nav": 8.2396
  },
  {
    "navdate": "2022-09-12",
    "nav": 8.7873
  },
  {
    "navdate": "2022-09-09",
    "nav": 8.68
  },
  {
    "navdate": "2022-09-08",
    "nav": 8.5001
  },
  {
    "navdate": "2022-09-07",
    "nav": 8.4836
  },
  {
    "navdate": "2022-09-06",
    "nav": 8.3103
  },
  {
    "navdate": "2022-09-02",
    "nav": 8.3609
  },
  {
    "navdate": "2022-09-01",
    "nav": 8.4423
  },
  {
    "navdate": "2022-08-30",
    "nav": 8.5219
  },
  {
    "navdate": "2022-08-29",
    "nav": 8.6586
  },
  {
    "navdate": "2022-08-26",
    "nav": 8.7234
  },
  {
    "navdate": "2022-08-25",
    "nav": 9.0914
  },
  {
    "navdate": "2022-08-24",
    "nav": 8.9286
  },
  {
    "navdate": "2022-08-23",
    "nav": 8.9146
  },
  {
    "navdate": "2022-08-22",
    "nav": 8.9187
  },
  {
    "navdate": "2022-08-19",
    "nav": 9.1473
  },
  {
    "navdate": "2022-08-18",
    "nav": 9.3181
  },
  {
    "navdate": "2022-08-17",
    "nav": 9.2667
  },
  {
    "navdate": "2022-08-16",
    "nav": 9.4086
  },
  {
    "navdate": "2022-08-12",
    "nav": 9.362
  },
  {
    "navdate": "2022-08-11",
    "nav": 9.1501
  },
  {
    "navdate": "2022-08-10",
    "nav": 9.2103
  },
  {
    "navdate": "2022-08-08",
    "nav": 9.0688
  },
  {
    "navdate": "2022-08-05",
    "nav": 9.0498
  },
  {
    "navdate": "2022-08-04",
    "nav": 9.1683
  },
  {
    "navdate": "2022-08-03",
    "nav": 9.0485
  },
  {
    "navdate": "2022-08-02",
    "nav": 8.7844
  },
  {
    "navdate": "2022-08-01",
    "nav": 8.8735
  },
  {
    "navdate": "2022-07-29",
    "nav": 8.9078
  },
  {
    "navdate": "2022-07-28",
    "nav": 8.7854
  },
  {
    "navdate": "2022-07-27",
    "nav": 8.7219
  },
  {
    "navdate": "2022-07-26",
    "nav": 8.3562
  },
  {
    "navdate": "2022-07-25",
    "nav": 8.5278
  },
  {
    "navdate": "2022-07-22",
    "nav": 8.582
  },
  {
    "navdate": "2022-07-21",
    "nav": 8.7426
  },
  {
    "navdate": "2022-07-20",
    "nav": 8.6187
  },
  {
    "navdate": "2022-07-19",
    "nav": 8.4848
  },
  {
    "navdate": "2022-07-18",
    "nav": 8.2237
  },
  {
    "navdate": "2022-07-15",
    "nav": 8.299
  },
  {
    "navdate": "2022-07-14",
    "nav": 8.1502
  },
  {
    "navdate": "2022-07-13",
    "nav": 8.1017
  },
  {
    "navdate": "2022-07-12",
    "nav": 8.1104
  },
  {
    "navdate": "2022-07-11",
    "nav": 8.1661
  },
  {
    "navdate": "2022-07-08",
    "nav": 8.3319
  },
  {
    "navdate": "2022-07-07",
    "nav": 8.2973
  },
  {
    "navdate": "2022-07-06",
    "nav": 8.1537
  },
  {
    "navdate": "2022-07-05",
    "nav": 8.0792
  },
  {
    "navdate": "2022-07-01",
    "nav": 7.9467
  },
  {
    "navdate": "2022-06-30",
    "nav": 7.875
  },
  {
    "navdate": "2022-06-29",
    "nav": 7.9801
  },
  {
    "navdate": "2022-06-28",
    "nav": 7.9418
  },
  {
    "navdate": "2022-06-27",
    "nav": 8.1533
  },
  {
    "navdate": "2022-06-24",
    "nav": 8.2243
  },
  {
    "navdate": "2022-06-23",
    "nav": 7.9416
  },
  {
    "navdate": "2022-06-22",
    "nav": 7.8214
  },
  {
    "navdate": "2022-06-21",
    "nav": 7.8223
  },
  {
    "navdate": "2022-06-20",
    "nav": 7.6241
  },
  {
    "navdate": "2022-06-17",
    "nav": 7.6336
  },
  {
    "navdate": "2022-06-16",
    "nav": 7.5406
  },
  {
    "navdate": "2022-06-15",
    "nav": 7.8536
  },
  {
    "navdate": "2022-06-14",
    "nav": 7.6566
  },
  {
    "navdate": "2022-06-13",
    "nav": 7.6539
  },
  {
    "navdate": "2022-06-10",
    "nav": 7.991
  },
  {
    "navdate": "2022-06-09",
    "nav": 8.2796
  },
  {
    "navdate": "2022-06-08",
    "nav": 8.5053
  },
  {
    "navdate": "2022-06-07",
    "nav": 8.5705
  },
  {
    "navdate": "2022-06-06",
    "nav": 8.4894
  },
  {
    "navdate": "2022-06-03",
    "nav": 8.4475
  },
  {
    "navdate": "2022-06-02",
    "nav": 8.6782
  },
  {
    "navdate": "2022-06-01",
    "nav": 8.4427
  },
  {
    "navdate": "2022-05-31",
    "nav": 8.5173
  },
  {
    "navdate": "2022-05-27",
    "nav": 8.5439
  },
  {
    "navdate": "2022-05-26",
    "nav": 8.2683
  },
  {
    "navdate": "2022-05-25",
    "nav": 8.0325
  },
  {
    "navdate": "2022-05-24",
    "nav": 7.928
  },
  {
    "navdate": "2022-05-23",
    "nav": 8.1014
  },
  {
    "navdate": "2022-05-20",
    "nav": 7.9679
  },
  {
    "navdate": "2022-05-19",
    "nav": 8.0062
  },
  {
    "navdate": "2022-05-18",
    "nav": 8.0291
  },
  {
    "navdate": "2022-05-17",
    "nav": 8.4636
  },
  {
    "navdate": "2022-05-16",
    "nav": 8.2164
  },
  {
    "navdate": "2022-05-13",
    "nav": 8.3129
  },
  {
    "navdate": "2022-05-12",
    "nav": 8.041
  },
  {
    "navdate": "2022-05-11",
    "nav": 8.0215
  },
  {
    "navdate": "2022-05-10",
    "nav": 8.2843
  },
  {
    "navdate": "2022-05-09",
    "nav": 8.1804
  },
  {
    "navdate": "2022-05-06",
    "nav": 8.4515
  },
  {
    "navdate": "2022-05-05",
    "nav": 8.4812
  },
  {
    "navdate": "2022-05-04",
    "nav": 8.9779
  },
  {
    "navdate": "2022-05-02",
    "nav": 8.6688
  },
  {
    "navdate": "2022-04-29",
    "nav": 8.5219
  },
  {
    "navdate": "2022-04-28",
    "nav": 8.9425
  },
  {
    "navdate": "2022-04-27",
    "nav": 8.6451
  },
  {
    "navdate": "2022-04-26",
    "nav": 8.641
  },
  {
    "navdate": "2022-04-25",
    "nav": 9.0079
  },
  {
    "navdate": "2022-04-22",
    "nav": 8.8448
  },
  {
    "navdate": "2022-04-21",
    "nav": 9.0707
  },
  {
    "navdate": "2022-04-20",
    "nav": 9.2798
  },
  {
    "navdate": "2022-04-19",
    "nav": 9.403
  },
  {
    "navdate": "2022-04-18",
    "nav": 9.2167
  },
  {
    "navdate": "2022-04-13",
    "nav": 9.4029
  },
  {
    "navdate": "2022-04-12",
    "nav": 9.2069
  },
  {
    "navdate": "2022-04-11",
    "nav": 9.2217
  },
  {
    "navdate": "2022-04-08",
    "nav": 9.4211
  },
  {
    "navdate": "2022-04-07",
    "nav": 9.5582
  },
  {
    "navdate": "2022-04-06",
    "nav": 9.5115
  },
  {
    "navdate": "2022-04-05",
    "nav": 9.6949
  },
  {
    "navdate": "2022-04-04",
    "nav": 9.9365
  },
  {
    "navdate": "2022-04-01",
    "nav": 9.7746
  },
  {
    "navdate": "2022-03-31",
    "nav": 9.7599
  },
  {
    "navdate": "2022-03-30",
    "nav": 9.9079
  },
  {
    "navdate": "2022-03-29",
    "nav": 10.0448
  },
  {
    "navdate": "2022-03-28",
    "nav": 9.9161
  },
  {
    "navdate": "2022-03-25",
    "nav": 9.7531
  },
  {
    "navdate": "2022-03-24",
    "nav": 9.7818
  },
  {
    "navdate": "2022-03-23",
    "nav": 9.5517
  },
  {
    "navdate": "2022-03-22",
    "nav": 9.7137
  },
  {
    "navdate": "2022-03-21",
    "nav": 9.4985
  },
  {
    "navdate": "2022-03-17",
    "nav": 9.2996
  },
  {
    "navdate": "2022-03-16",
    "nav": 9.2479
  },
  {
    "navdate": "2022-03-15",
    "nav": 8.9348
  },
  {
    "navdate": "2022-03-14",
    "nav": 8.6755
  },
  {
    "navdate": "2022-03-11",
    "nav": 8.8247
  },
  {
    "navdate": "2022-03-10",
    "nav": 8.979
  },
  {
    "navdate": "2022-03-09",
    "nav": 9.1668
  },
  {
    "navdate": "2022-03-08",
    "nav": 8.8534
  },
  {
    "navdate": "2022-03-07",
    "nav": 8.8928
  },
  {
    "navdate": "2022-03-04",
    "nav": 9.144
  },
  {
    "navdate": "2022-03-03",
    "nav": 9.2241
  },
  {
    "navdate": "2022-03-02",
    "nav": 9.3614
  },
  {
    "navdate": "2022-02-28",
    "nav": 9.3293
  },
  {
    "navdate": "2022-02-25",
    "nav": 9.2726
  },
  {
    "navdate": "2022-02-24",
    "nav": 9.1294
  },
  {
    "navdate": "2022-02-23",
    "nav": 8.7521
  },
  {
    "navdate": "2022-02-22",
    "nav": 9.0159
  },
  {
    "navdate": "2022-02-18",
    "nav": 9.1128
  },
  {
    "navdate": "2022-02-17",
    "nav": 9.238
  },
  {
    "navdate": "2022-02-16",
    "nav": 9.5174
  },
  {
    "navdate": "2022-02-15",
    "nav": 9.6005
  },
  {
    "navdate": "2022-02-14",
    "nav": 9.3582
  },
  {
    "navdate": "2022-02-11",
    "nav": 9.3244
  },
  {
    "navdate": "2022-02-10",
    "nav": 9.5635
  },
  {
    "navdate": "2022-02-09",
    "nav": 9.7764
  },
  {
    "navdate": "2022-02-08",
    "nav": 9.5592
  },
  {
    "navdate": "2022-02-07",
    "nav": 9.4497
  },
  {
    "navdate": "2022-02-04",
    "nav": 9.5304
  },
  {
    "navdate": "2022-02-03",
    "nav": 9.4213
  },
  {
    "navdate": "2022-02-02",
    "nav": 9.8304
  },
  {
    "navdate": "2022-02-01",
    "nav": 9.7149
  },
  {
    "navdate": "2022-01-31",
    "nav": 9.7119
  },
  {
    "navdate": "2022-01-28",
    "nav": 9.4025
  },
  {
    "navdate": "2022-01-27",
    "nav": 9.1344
  },
  {
    "navdate": "2022-01-25",
    "nav": 9.1781
  },
  {
    "navdate": "2022-01-24",
    "nav": 9.3893
  },
  {
    "navdate": "2022-01-21",
    "nav": 9.3396
  },
  {
    "navdate": "2022-01-20",
    "nav": 9.5814
  },
  {
    "navdate": "2022-01-19",
    "nav": 9.7423
  },
  {
    "navdate": "2022-01-18",
    "nav": 9.8246
  },
  {
    "navdate": "2022-01-14",
    "nav": 10.0444
  },
  {
    "navdate": "2022-01-13",
    "nav": 9.9461
  },
  {
    "navdate": "2022-01-12",
    "nav": 10.2174
  },
  {
    "navdate": "2022-01-11",
    "nav": 10.17
  },
  {
    "navdate": "2022-01-10",
    "nav": 10.0535
  },
  {
    "navdate": "2022-01-07",
    "nav": 10.0569
  },
  {
    "navdate": "2022-01-06",
    "nav": 10.1882
  },
  {
    "navdate": "2022-01-05",
    "nav": 10.1986
  },
  {
    "navdate": "2022-01-04",
    "nav": 10.5392
  },
  {
    "navdate": "2022-01-03",
    "nav": 10.6446
  },
  {
    "navdate": "2021-12-31",
    "nav": 10.5275
  },
  {
    "navdate": "2021-12-30",
    "nav": 10.6371
  },
  {
    "navdate": "2021-12-29",
    "nav": 10.6994
  },
  {
    "navdate": "2021-12-28",
    "nav": 10.714
  },
  {
    "navdate": "2021-12-27",
    "nav": 10.804
  },
  {
    "navdate": "2021-12-23",
    "nav": 10.6706
  },
  {
    "navdate": "2021-12-22",
    "nav": 10.6231
  },
  {
    "navdate": "2021-12-21",
    "nav": 10.4954
  },
  {
    "navdate": "2021-12-20",
    "nav": 10.3128
  },
  {
    "navdate": "2021-12-17",
    "nav": 10.4533
  },
  {
    "navdate": "2021-12-16",
    "nav": 10.5064
  },
  {
    "navdate": "2021-12-15",
    "nav": 10.7591
  },
  {
    "navdate": "2021-12-14",
    "nav": 10.4922
  },
  {
    "navdate": "2021-12-13",
    "nav": 10.5749
  },
  {
    "navdate": "2021-12-10",
    "nav": 10.7408
  },
  {
    "navdate": "2021-12-09",
    "nav": 10.5909
  },
  {
    "navdate": "2021-12-08",
    "nav": 10.7472
  },
  {
    "navdate": "2021-12-07",
    "nav": 10.6856
  },
  {
    "navdate": "2021-12-06",
    "nav": 10.3669
  },
  {
    "navdate": "2021-12-03",
    "nav": 10.2384
  },
  {
    "navdate": "2021-12-02",
    "nav": 10.4209
  },
  {
    "navdate": "2021-12-01",
    "nav": 10.3362
  },
  {
    "navdate": "2021-11-30",
    "nav": 10.528
  },
  {
    "navdate": "2021-11-29",
    "nav": 10.7001
  },
  {
    "navdate": "2021-11-26",
    "nav": 10.4065
  },
  {
    "navdate": "2021-11-24",
    "nav": 10.5846
  },
  {
    "navdate": "2021-11-23",
    "nav": 10.5593
  },
  {
    "navdate": "2021-11-22",
    "nav": 10.5902
  },
  {
    "navdate": "2021-11-18",
    "nav": 10.6257
  },
  {
    "navdate": "2021-11-17",
    "nav": 10.5443
  },
  {
    "navdate": "2021-11-16",
    "nav": 10.5552
  },
  {
    "navdate": "2021-11-15",
    "nav": 10.4639
  },
  {
    "navdate": "2021-11-12",
    "nav": 10.4872
  },
  {
    "navdate": "2021-11-11",
    "nav": 10.3798
  },
  {
    "navdate": "2021-11-10",
    "nav": 10.3077
  },
  {
    "navdate": "2021-11-09",
    "nav": 10.4223
  },
  {
    "navdate": "2021-11-08",
    "nav": 10.5227
  },
  {
    "navdate": "2021-11-03",
    "nav": 10.4631
  },
  {
    "navdate": "2021-11-02",
    "nav": 10.3794
  },
  {
    "navdate": "2021-11-01",
    "nav": 10.36
  },
  {
    "navdate": "2021-10-29",
    "nav": 10.3
  },
  {
    "navdate": "2021-10-28",
    "nav": 10.26
  },
  {
    "navdate": "2021-10-27",
    "nav": 10.16
  },
  {
    "navdate": "2021-10-26",
    "nav": 10.16
  },
  {
    "navdate": "2021-10-25",
    "nav": 10.12
  },
  {
    "navdate": "2021-10-22",
    "nav": 9.99
  },
  {
    "navdate": "2021-10-21",
    "nav": 10.07
  },
  {
    "navdate": "2021-10-19",
    "nav": 10.07
  }
]